pyxtensor/__init__.py
pyxtensor-0.3.1.data/headers/pybind11_xarray.hpp
pyxtensor-0.3.1.data/headers/pybind11_xtensor.hpp
pyxtensor-0.3.1.data/headers/pybind11_xtensor_fixed.hpp
pyxtensor-0.3.1.data/headers/pyxtensor.hpp
pyxtensor-0.3.1.dist-info/LICENSE
pyxtensor-0.3.1.dist-info/METADATA
pyxtensor-0.3.1.dist-info/WHEEL
pyxtensor-0.3.1.dist-info/top_level.txt
pyxtensor-0.3.1.dist-info/RECORD
