Metadata-Version: 2.1
Name: pyxtensor
Version: 0.3.1
Summary: pybind11 details for xtensor
Home-page: https://github.com/tdegeus/pyxtensor
Author: Tom de Geus
Author-email: tom@geus.me
License: MIT
Keywords: C++,C++11,C++14,Python bindings,pybind11,xtensor
Platform: UNKNOWN
Requires-Dist: pybind11 (>=2.2.0)
